evafs/__init__.py
evafs/cli.py
evafs/webapp.py
evafs/webservice.py
evafs-0.0.11.dist-info/LICENSE.txt
evafs-0.0.11.dist-info/METADATA
evafs-0.0.11.dist-info/WHEEL
evafs-0.0.11.dist-info/entry_points.txt
evafs-0.0.11.dist-info/top_level.txt
evafs-0.0.11.dist-info/RECORD
