Metadata-Version: 2.1
Name: evafs
Version: 0.0.11
Summary: A storage system middleware
Home-page: https://github.com/pyscaffold/pyscaffold/
Author: sanchezcarlosjr
Author-email: 24639141+sanchezcarlosjr@users.noreply.github.com
License: MIT
Project-URL: Documentation, https://pyscaffold.org/
Platform: any
Classifier: Development Status :: 4 - Beta
Classifier: Programming Language :: Python
License-File: LICENSE.txt
Requires-Dist: typer[all]
Requires-Dist: gradio
Requires-Dist: pydantic
Requires-Dist: dagster
Requires-Dist: ray[serve]
Requires-Dist: fastapi
Requires-Dist: importlib-metadata ; python_version < "3.10"
Provides-Extra: testing
Requires-Dist: setuptools ; extra == 'testing'
Requires-Dist: pytest ; extra == 'testing'
Requires-Dist: pytest-cov ; extra == 'testing'
